README.txt
setup.py
ekuerre/__init__.py
ekuerre/main.py
ekuerre.egg-info/PKG-INFO
ekuerre.egg-info/SOURCES.txt
ekuerre.egg-info/dependency_links.txt
ekuerre.egg-info/requires.txt
ekuerre.egg-info/top_level.txt