Metadata-Version: 1.0
Name: ekuerre
Version: 1.0.0b1
Summary: QR web service provider
Home-page: https://github.com/gamikun/ekuerre
Author: Gamaliel Espinoza M.
Author-email: gamaliel.espinoza@gmail.com
License: UNKNOWN
Keywords: qr,api,png
Platform: UNKNOWN
